heatchmap/__init__.py
heatchmap/gpmap.py
heatchmap/map_based_model.py
heatchmap/models.py
heatchmap/weighted_average_gaussian.py
heatchmap/utils/__init__.py
heatchmap/utils/numeric_transformers.py
heatchmap/utils/plotting.py
heatchmap/utils/transformed_target_regressor_with_uncertainty.py
heatchmap/utils/utils_data.py
heatchmap/utils/utils_map.py
heatchmap/utils/utils_models.py
heatchmap-0.2.9.dist-info/licenses/LICENSE
heatchmap-0.2.9.dist-info/METADATA
heatchmap-0.2.9.dist-info/WHEEL
heatchmap-0.2.9.dist-info/top_level.txt
heatchmap-0.2.9.dist-info/RECORD
