Metadata-Version: 2.4
Name: heatchmap
Version: 0.2.9
Summary: A package for estimation and visualization of hitchhiking quality.
Home-page: https://github.com/Hitchwiki/heatchmap
Author: Hitchwiki
Author-email: info@hitchwiki.org
License: MIT
Project-URL: Source Code, https://github.com/Hitchwiki/heatchmap
Classifier: Intended Audience :: Science/Research
Classifier: License :: OSI Approved :: MIT License
Classifier: Programming Language :: Python :: 3
Classifier: Operating System :: OS Independent
Requires-Python: >=3.10
License-File: LICENSE
Requires-Dist: datasets>=3.2.0
Requires-Dist: huggingface-hub>=0.27.1
Requires-Dist: geopandas>=1.0.1
Requires-Dist: matplotlib>=3.10.0
Requires-Dist: numpy>=2.2.1
Requires-Dist: osmnx>=1.7.0
Requires-Dist: pandas>=2.2.3
Requires-Dist: rasterio>=1.4.3
Requires-Dist: scikit-learn>=1.6.0
Requires-Dist: scipy>=1.15.0
Requires-Dist: shapely>=2.0.6
Requires-Dist: tqdm>=4.67.1
Dynamic: author
Dynamic: author-email
Dynamic: classifier
Dynamic: description
Dynamic: description-content-type
Dynamic: home-page
Dynamic: license
Dynamic: license-file
Dynamic: project-url
Dynamic: requires-dist
Dynamic: requires-python
Dynamic: summary
